{"errors":[],"warnings":[],"namedChunkGroups":{"polyfill":{"chunks":[2,10],"assets":["webpack-runtime-3ba70e10376f45b99a56.js","webpack-runtime-3ba70e10376f45b99a56.js.map","polyfill-2966d4d8fea208fd6f8f.js","polyfill-2966d4d8fea208fd6f8f.js.map"],"children":{},"childAssets":{}},"app":{"chunks":[2,9,4,3],"assets":["webpack-runtime-3ba70e10376f45b99a56.js","webpack-runtime-3ba70e10376f45b99a56.js.map","framework-741ade27086b2708e961.js","framework-741ade27086b2708e961.js.map","bcdce425-00254e16c28faa2f5d39.js","bcdce425-00254e16c28faa2f5d39.js.map","app-8eff7ca25941a9a97824.js","app-8eff7ca25941a9a97824.js.map"],"children":{},"childAssets":{}},"component---src-pages-404-js":{"chunks":[1,0,5],"assets":["styles.d5ef0abb16ee382cea7f.css","styles-e9d24b1846c7d6eb9685.js","styles-e9d24b1846c7d6eb9685.js.map","commons-275d34883ac268dab99f.js","commons-275d34883ac268dab99f.js.map","component---src-pages-404-js-92650dac53357cd251f9.js","component---src-pages-404-js-92650dac53357cd251f9.js.map"],"children":{},"childAssets":{}},"component---src-pages-index-js":{"chunks":[1,0,6],"assets":["styles.d5ef0abb16ee382cea7f.css","styles-e9d24b1846c7d6eb9685.js","styles-e9d24b1846c7d6eb9685.js.map","commons-275d34883ac268dab99f.js","commons-275d34883ac268dab99f.js.map","component---src-pages-index-js-c785dab16ac3a78d62d4.js","component---src-pages-index-js-c785dab16ac3a78d62d4.js.map"],"children":{},"childAssets":{}},"component---src-pages-new-js":{"chunks":[1,0,7],"assets":["styles.d5ef0abb16ee382cea7f.css","styles-e9d24b1846c7d6eb9685.js","styles-e9d24b1846c7d6eb9685.js.map","commons-275d34883ac268dab99f.js","commons-275d34883ac268dab99f.js.map","component---src-pages-new-js-928e7414cce048045c51.js","component---src-pages-new-js-928e7414cce048045c51.js.map"],"children":{},"childAssets":{}},"component---src-pages-poll-js":{"chunks":[1,0,8],"assets":["styles.d5ef0abb16ee382cea7f.css","styles-e9d24b1846c7d6eb9685.js","styles-e9d24b1846c7d6eb9685.js.map","commons-275d34883ac268dab99f.js","commons-275d34883ac268dab99f.js.map","component---src-pages-poll-js-dd5ea3d0020ead273d4b.js","component---src-pages-poll-js-dd5ea3d0020ead273d4b.js.map"],"children":{},"childAssets":{}}},"assetsByChunkName":{"polyfill":["webpack-runtime-3ba70e10376f45b99a56.js","polyfill-2966d4d8fea208fd6f8f.js"],"app":["webpack-runtime-3ba70e10376f45b99a56.js","framework-741ade27086b2708e961.js","bcdce425-00254e16c28faa2f5d39.js","app-8eff7ca25941a9a97824.js"],"component---src-pages-404-js":["styles.d5ef0abb16ee382cea7f.css","styles-e9d24b1846c7d6eb9685.js","commons-275d34883ac268dab99f.js","component---src-pages-404-js-92650dac53357cd251f9.js"],"component---src-pages-index-js":["styles.d5ef0abb16ee382cea7f.css","styles-e9d24b1846c7d6eb9685.js","commons-275d34883ac268dab99f.js","component---src-pages-index-js-c785dab16ac3a78d62d4.js"],"component---src-pages-new-js":["styles.d5ef0abb16ee382cea7f.css","styles-e9d24b1846c7d6eb9685.js","commons-275d34883ac268dab99f.js","component---src-pages-new-js-928e7414cce048045c51.js"],"component---src-pages-poll-js":["styles.d5ef0abb16ee382cea7f.css","styles-e9d24b1846c7d6eb9685.js","commons-275d34883ac268dab99f.js","component---src-pages-poll-js-dd5ea3d0020ead273d4b.js"]}}